{
  "name": "speaker-images/15344117-6751-48a8-91ee-6e0f8fdfa094-square.png",
  "bucket": "urm-app-images",
  "metageneration": 2,
  "generation": 1668323705741,
  "contentType": "image/png",
  "storageClass": "STANDARD",
  "downloadTokens": [],
  "etag": "WeMnYwtkmVPsxjMzfvGxKk8UnSQ",
  "timeCreated": "2022-11-13T07:15:05.741Z",
  "updated": "2022-11-13T07:15:05.754Z",
  "size": 34513,
  "md5Hash": "+UotGfd5HjEwtTBWcK6sVg==",
  "crc32c": "2242957798",
  "customMetadata": {
    "width": "372",
    "height": "554",
    "average_color_hex": "#65473a",
    "vibrant_color_hex": "#7b3620"
  }
}