{
  "name": "speaker-images/bf894720-8377-4abd-9955-ea58d87111ca-wide.jpeg",
  "bucket": "urm-app-images",
  "metageneration": 3,
  "generation": 1668323695108,
  "contentType": "image/jpeg",
  "storageClass": "STANDARD",
  "downloadTokens": [
    "6c0e42ae-d535-46fa-a131-21c069700481"
  ],
  "etag": "2Oi8unMS3a/0n1y9lOsxvLdX2O8",
  "customMetadata": {
    "width": "1920",
    "height": "1080",
    "average_color_hex": "#d4cfca",
    "vibrant_color_hex": "#4a4a49"
  },
  "timeCreated": "2022-11-13T07:14:55.108Z",
  "updated": "2022-11-14T20:35:41.408Z",
  "size": 282064,
  "md5Hash": "tYOaQ5ChYqjVYG+67nexJw==",
  "crc32c": "1534878798"
}