{
  "name": "speaker-images/04d0fb76-6f5a-43a5-924d-68efef3e0f50-wide.jpeg",
  "bucket": "urm-app-images",
  "metageneration": 3,
  "generation": 1668323709052,
  "contentType": "image/jpeg",
  "storageClass": "STANDARD",
  "downloadTokens": [
    "4b8ed71b-9ce1-4bac-8568-d0954a272da0"
  ],
  "etag": "2/pubAXpLuQl7TR9tQw9f8LZRYw",
  "customMetadata": {
    "width": "1920",
    "height": "1080",
    "average_color_hex": "#d7cecb",
    "vibrant_color_hex": "#d9c0b3"
  },
  "timeCreated": "2022-11-13T07:15:09.052Z",
  "updated": "2022-11-14T20:35:41.804Z",
  "size": 308520,
  "md5Hash": "+GCEzqN94g4ccGXF6OW83g==",
  "crc32c": "901987713"
}