{
  "name": "speaker-images/cc3a27e3-1fd0-471f-8151-08c0f37c809d-banner.jpeg",
  "bucket": "urm-app-images",
  "metageneration": 3,
  "generation": 1668323708464,
  "contentType": "image/jpeg",
  "storageClass": "STANDARD",
  "downloadTokens": [
    "7d546ef2-6f51-4dea-a7dc-2324f350ebd5"
  ],
  "etag": "eWsJTFMYTl7tjrJBG3KdsXe8Ju0",
  "customMetadata": {
    "width": "1920",
    "height": "692",
    "average_color_hex": "#9c9086",
    "vibrant_color_hex": "#f1d0ba"
  },
  "timeCreated": "2022-11-13T07:15:08.464Z",
  "updated": "2022-11-14T20:35:41.591Z",
  "size": 145548,
  "md5Hash": "USM6or3UlI93KtCv2GoaXQ==",
  "crc32c": "3015725930"
}