{
  "name": "speaker-images/b658d048-b5b6-4cdd-82ed-070e9033c5a0-square.jpeg",
  "bucket": "urm-app-images",
  "metageneration": 3,
  "generation": 1668323696573,
  "contentType": "image/jpeg",
  "storageClass": "STANDARD",
  "downloadTokens": [
    "67f83864-74c9-44f1-8369-d7293e37d376"
  ],
  "etag": "JWFGoGgNgtTZ3W2n+aqJIl5RtwU",
  "customMetadata": {
    "width": "340",
    "height": "340",
    "average_color_hex": "#806a4d",
    "vibrant_color_hex": "#16b49c"
  },
  "timeCreated": "2022-11-13T07:14:56.573Z",
  "updated": "2022-11-14T20:35:42.426Z",
  "size": 32602,
  "md5Hash": "Bo/OIflQtNp5Pg5o/DU5dA==",
  "crc32c": "1503577939"
}