{
  "name": "intro-outro-sermons/bb1361eb-d9b8-4018-beda-9c19679c0cc1",
  "bucket": "urm-app.appspot.com",
  "metageneration": 3,
  "generation": 1675442888198,
  "contentType": "audio/mpeg",
  "storageClass": "STANDARD",
  "downloadTokens": [
    "49f60d55-5f28-4554-9f96-de09b1cff70f"
  ],
  "etag": "bRc5IL/CrG+AJz+tCAwCFZOpaZQ",
  "timeCreated": "2023-02-03T16:48:08.198Z",
  "updated": "2023-02-03T16:48:53.750Z",
  "size": 468719,
  "md5Hash": "yfLfaxQQ7q2GMUnv1Fc4mw==",
  "crc32c": "3009254838"
}