{
  "name": "speaker-images/4f69502c-a800-469d-8f37-95eb47ce1a08-square.jpeg",
  "bucket": "urm-app-images",
  "metageneration": 2,
  "generation": 1669077170887,
  "contentType": "image/jpeg",
  "storageClass": "STANDARD",
  "downloadTokens": [],
  "etag": "B4L/NkNMAhTjRyfvZHRJ+hcSc/A",
  "timeCreated": "2022-11-22T00:32:50.887Z",
  "updated": "2022-11-22T00:32:51.637Z",
  "size": 105274,
  "md5Hash": "aSosfC4i6MSFGaqcT9Ni6g==",
  "crc32c": "2816587262",
  "customMetadata": {
    "width": "1202",
    "height": "1202",
    "average_color_hex": "#554b45",
    "vibrant_color_hex": "#947e6f"
  }
}