{
  "name": "speaker-images/cd509539-c1af-494d-a053-e68edbab3542-wide.jpeg",
  "bucket": "urm-app-images",
  "metageneration": 2,
  "generation": 1668323699558,
  "contentType": "image/jpeg",
  "storageClass": "STANDARD",
  "downloadTokens": [],
  "etag": "bwlvoxAb01O0rdYzzklrX6k2G7Y",
  "timeCreated": "2022-11-13T07:14:59.558Z",
  "updated": "2022-11-13T07:14:59.562Z",
  "size": 113459,
  "md5Hash": "jOTCreLOjy3IlDtvFL4/Og==",
  "crc32c": "3003327198",
  "customMetadata": {
    "width": "1600",
    "height": "900",
    "average_color_hex": "#735d48",
    "vibrant_color_hex": "#f4bb9d"
  }
}